{
  "BlockType": {
    "DrawType": "Model",
    "CustomModel": "Blocks/Furniture/Carpets/Carpet_Octagon.blockymodel",
    "Group": "Cloth",
    "CustomModelTexture": [
      {
        "Texture": "Resources/Carpets/Carpet_Octagon_Royal.png"
      }
    ],
    "HitboxType": "Carpet_Octagon",
    "Material": "Solid",
    "Opacity": "Transparent",
    "BlockParticleSetId": "Grass",
    "Gathering": {
      "Soft": {}
    },
    "BlockSoundSetId": "Cloth",
    "PhysicalMaterialId": "Wool",
    "ParticleColor": "#7e1919",
    "Support": {
      "Down": [
        {
          "FaceType": "Full",
          "Support": "Required"
        }
      ]
    }
  },
  "Interactions": {
    "Primary": "Block_Primary",
    "Secondary": "Block_Secondary"
  },
  "Categories": [
    "HR_CoreCreator.Decoration"
  ],
  "PlayerAnimationsId": "Item",
  "ItemSoundSetId": "ISS_Items_Cloth",
  "Quality": "Template",
  "IconProperties": {
    "Scale": 0.26,
    "Rotation": [
      22.5,
      49,
      24
    ],
    "Translation": [
      -22.5,
      0
    ]
  },
  "Tags": {
    "Type": [
      "Furniture"
    ]
  },
  "SubCategory": "Carpets"
}
